py_mp/__init__.py
py_mp/commands/__init__.py
py_mp/commands/commands.py
py_mp/commands/flags.py
py_mp/models/__init__.py
py_mp/models/network.py
py_mp/network/__init__.py
py_mp/network/client.py
py_mp/network/server.py
python_multiplayer-0.1.2.dist-info/LICENSE
python_multiplayer-0.1.2.dist-info/METADATA
python_multiplayer-0.1.2.dist-info/WHEEL
python_multiplayer-0.1.2.dist-info/RECORD
